rsyncs3/__init__.py
rsyncs3/rsyncS3.py
rsyncs3-0.2.0.dist-info/WHEEL
rsyncs3-0.2.0.dist-info/METADATA
rsyncs3-0.2.0.dist-info/RECORD
